Lab1.srcs/sources_1/imports/old/clock_enable.vhd
--This module is to generate an enable signal for different display frequency based on pushbuttons
-- Fill in the blank to complete this module 
-- (c) Rajesh Panicker, ECE, NUS

library ieee;
use ieee.std_logic_1164.all;
use ieee.numeric_std.all;

entity clock_enable is
  port(
    clk : in std_logic; -- fundamental clock 1MHz
    btnU : in std_logic; -- button BTNU for 4Hz speed
    btnC : in std_logic; -- button BTNC for pause
    enable : out std_logic -- output signal used to enable the reading of next memory data
  );
end clock_enable;

architecture behavioral of clock_enable is
  signal counter : std_logic_vector(19 downto 0) := x"00000";
begin
  process(clk)
    -- constant speed_one : std_logic_vector(19 downto 0) := x"F4240";
    -- constant speed_four : std_logic_vector(19 downto 0) := x"3D090";
    -- For simulations
    constant speed_one : std_logic_vector(19 downto 0) := x"00064";
    constant speed_four : std_logic_vector(19 downto 0) := x"00019";
  begin
    if rising_edge(clk) then
      if btnC = '1' then
        enable <= '0';
      else
        counter <= std_logic_vector(unsigned(counter) + 1);
        if (btnU = '1' and counter >= speed_one) or (btnU = '0' and counter >= speed_four) then
          enable <= '1';
          counter <= x"00000";
        else
          enable <= '0';
        end if;
      end if;
    end if;
  end process;
end behavioral;

Lab1.srcs/sim_1/imports/old/clock_enable_tb.vhd
library ieee;
use ieee.std_logic_1164.all;
use ieee.numeric_std.all;

entity clock_enable_tb is
end clock_enable_tb;

architecture behavioral of clock_enable_tb is
  component clock_enable
    port(
      clk : in std_logic;
      btnU : in std_logic;
      btnC : in std_logic;
      enable : out std_logic
    );
  end component;
  signal clk : std_logic := '1';
  signal btnU, btnC, enable : std_logic;
begin
  dut : clock_enable port map (
    clk => clk,
    btnU => btnU,
    btnC => btnC,
    enable => enable
  );

  process 
  begin
    clk <= '1';
    wait for 5 ns;
    clk <= '0';
    wait for 5 ns;
  end process;

  process
  begin
    btnC <= '1';
    btnU <= '1';
    wait for 40 ns;
    btnC <= '0';
    btnU <= '0';
    wait for 40 ns;
    btnC <= '0';
    btnU <= '1';
    wait for 40 ns;
    wait;
  end process;
end behavioral;

clock_enable_tb.vcd
$date
  Sun Sep  8 16:48:44 2019
$end
$version
  GHDL v0
$end
$timescale
  1 fs
$end
$scope module standard $end
$upscope $end
$scope module std_logic_1164 $end
$upscope $end
$scope module numeric_std $end
$upscope $end
$scope module clock_enable_tb $end
$var reg 1 ! clk $end
$var reg 1 " btnu $end
$var reg 1 # btnc $end
$var reg 1 $ enable $end
$scope module dut $end
$var reg 1 % clk $end
$var reg 1 & btnu $end
$var reg 1 ' btnc $end
$var reg 1 ( enable $end
$var reg 20 ) counter[19:0] $end
$upscope $end
$upscope $end
$enddefinitions $end
#0
1!
1"
1#
U$
1%
1&
1'
U(
b00000000000000000000 )
#5000000
0!
0%
#10000000
1!
0$
1%
0(
#15000000
0!
0%
#20000000
1!
1%
#25000000
0!
0%
#30000000
1!
1%
#35000000
0!
0%
#40000000
1!
0"
0#
1%
0&
0'
b00000000000000000001 )
#45000000
0!
0%
#50000000
1!
1%
b00000000000000000010 )
#55000000
0!
0%
#60000000
1!
1%
b00000000000000000011 )
#65000000
0!
0%
#70000000
1!
1%
b00000000000000000100 )
#75000000
0!
0%
#80000000
1!
1"
1%
1&
b00000000000000000101 )
#85000000
0!
0%
#90000000
1!
1%
b00000000000000000110 )
#95000000
0!
0%
#100000000
1!
1%
b00000000000000000111 )
#105000000
0!
0%
#110000000
1!
1%
b00000000000000001000 )
#115000000
0!
0%
#120000000
1!
1%
b00000000000000001001 )
#125000000
0!
0%
#130000000
1!
1%
b00000000000000001010 )
#135000000
0!
0%
#140000000
1!
1%
b00000000000000001011 )
#145000000
0!
0%
#150000000
1!
1%
b00000000000000001100 )
#155000000
0!
0%
#160000000
1!
1%
b00000000000000001101 )
#165000000
0!
0%
#170000000
1!
1%
b00000000000000001110 )
#175000000
0!
0%
#180000000
1!
1%
b00000000000000001111 )
#185000000
0!
0%
#190000000
1!
1%
b00000000000000010000 )
#195000000
0!
0%
#200000000
1!
1%
b00000000000000010001 )
#205000000
0!
0%
#210000000
1!
1%
b00000000000000010010 )
#215000000
0!
0%
#220000000
1!
1%
b00000000000000010011 )
#225000000
0!
0%
#230000000
1!
1%
b00000000000000010100 )
#235000000
0!
0%
#240000000
1!
1%
b00000000000000010101 )
#245000000
0!
0%
#250000000
1!
1%
b00000000000000010110 )
#255000000
0!
0%
#260000000
1!
1%
b00000000000000010111 )
#265000000
0!
0%
#270000000
1!
1%
b00000000000000011000 )
#275000000
0!
0%
#280000000
1!
1%
b00000000000000011001 )
#285000000
0!
0%
#290000000
1!
1%
b00000000000000011010 )
#295000000
0!
0%
#300000000
1!
1%
b00000000000000011011 )
#305000000
0!
0%
#310000000
1!
1%
b00000000000000011100 )
#315000000
0!
0%
#320000000
1!
1%
b00000000000000011101 )
#325000000
0!
0%
#330000000
1!
1%
b00000000000000011110 )
#335000000
0!
0%
#340000000
1!
1%
b00000000000000011111 )
#345000000
0!
0%
#350000000
1!
1%
b00000000000000100000 )
#355000000
0!
0%
#360000000
1!
1%
b00000000000000100001 )
#365000000
0!
0%
#370000000
1!
1%
b00000000000000100010 )
#375000000
0!
0%
#380000000
1!
1%
b00000000000000100011 )
#385000000
0!
0%
#390000000
1!
1%
b00000000000000100100 )
#395000000
0!
0%
#400000000
1!
1%
b00000000000000100101 )
#405000000
0!
0%
#410000000
1!
1%
b00000000000000100110 )
#415000000
0!
0%
#420000000
1!
1%
b00000000000000100111 )
#425000000
0!
0%
#430000000
1!
1%
b00000000000000101000 )
#435000000
0!
0%
#440000000
1!
1%
b00000000000000101001 )
#445000000
0!
0%
#450000000
1!
1%
b00000000000000101010 )
#455000000
0!
0%
#460000000
1!
1%
b00000000000000101011 )
#465000000
0!
0%
#470000000
1!
1%
b00000000000000101100 )
#475000000
0!
0%
#480000000
1!
1%
b00000000000000101101 )
#485000000
0!
0%
#490000000
1!
1%
b00000000000000101110 )
#495000000
0!
0%
#500000000
1!
1%
b00000000000000101111 )
#505000000
0!
0%
#510000000
1!
1%
b00000000000000110000 )
#515000000
0!
0%
#520000000
1!
1%
b00000000000000110001 )
#525000000
0!
0%
#530000000
1!
1%
b00000000000000110010 )
#535000000
0!
0%
#540000000
1!
1%
b00000000000000110011 )
#545000000
0!
0%
#550000000
1!
1%
b00000000000000110100 )
#555000000
0!
0%
#560000000
1!
1%
b00000000000000110101 )
#565000000
0!
0%
#570000000
1!
1%
b00000000000000110110 )
#575000000
0!
0%
#580000000
1!
1%
b00000000000000110111 )
#585000000
0!
0%
#590000000
1!
1%
b00000000000000111000 )
#595000000
0!
0%
#600000000
1!
1%
b00000000000000111001 )
#605000000
0!
0%
#610000000
1!
1%
b00000000000000111010 )
#615000000
0!
0%
#620000000
1!
1%
b00000000000000111011 )
#625000000
0!
0%
#630000000
1!
1%
b00000000000000111100 )
#635000000
0!
0%
#640000000
1!
1%
b00000000000000111101 )
#645000000
0!
0%
#650000000
1!
1%
b00000000000000111110 )
#655000000
0!
0%
#660000000
1!
1%
b00000000000000111111 )
#665000000
0!
0%
#670000000
1!
1%
b00000000000001000000 )
#675000000
0!
0%
#680000000
1!
1%
b00000000000001000001 )
#685000000
0!
0%
#690000000
1!
1%
b00000000000001000010 )
#695000000
0!
0%
#700000000
1!
1%
b00000000000001000011 )
#705000000
0!
0%
#710000000
1!
1%
b00000000000001000100 )
#715000000
0!
0%
#720000000
1!
1%
b00000000000001000101 )
#725000000
0!
0%
#730000000
1!
1%
b00000000000001000110 )
#735000000
0!
0%
#740000000
1!
1%
b00000000000001000111 )
#745000000
0!
0%
#750000000
1!
1%
b00000000000001001000 )
#755000000
0!
0%
#760000000
1!
1%
b00000000000001001001 )
#765000000
0!
0%
#770000000
1!
1%
b00000000000001001010 )
#775000000
0!
0%
#780000000
1!
1%
b00000000000001001011 )
#785000000
0!
0%
#790000000
1!
1%
b00000000000001001100 )
#795000000
0!
0%
#800000000
1!
1%
b00000000000001001101 )
#805000000
0!
0%
#810000000
1!
1%
b00000000000001001110 )
#815000000
0!
0%
#820000000
1!
1%
b00000000000001001111 )
#825000000
0!
0%
#830000000
1!
1%
b00000000000001010000 )
#835000000
0!
0%
#840000000
1!
1%
b00000000000001010001 )
#845000000
0!
0%
#850000000
1!
1%
b00000000000001010010 )
#855000000
0!
0%
#860000000
1!
1%
b00000000000001010011 )
#865000000
0!
0%
#870000000
1!
1%
b00000000000001010100 )
#875000000
0!
0%
#880000000
1!
1%
b00000000000001010101 )
#885000000
0!
0%
#890000000
1!
1%
b00000000000001010110 )
#895000000
0!
0%
#900000000
1!
1%
b00000000000001010111 )
#905000000
0!
0%
#910000000
1!
1%
b00000000000001011000 )
#915000000
0!
0%
#920000000
1!
1%
b00000000000001011001 )
#925000000
0!
0%
#930000000
1!
1%
b00000000000001011010 )
#935000000
0!
0%
#940000000
1!
1%
b00000000000001011011 )
#945000000
0!
0%
#950000000
1!
1%
b00000000000001011100 )
#955000000
0!
0%
#960000000
1!
1%
b00000000000001011101 )
#965000000
0!
0%
#970000000
1!
1%
b00000000000001011110 )
#975000000
0!
0%
#980000000
1!
1%
b00000000000001011111 )
#985000000
0!
0%
#990000000
1!
1%
b00000000000001100000 )
#995000000
0!
0%
#1000000000
1!
1%
b00000000000001100001 )
#1005000000
0!
0%
#1010000000
1!
1%
b00000000000001100010 )
#1015000000
0!
0%
#1020000000
1!
1%
b00000000000001100011 )
#1025000000
0!
0%
#1030000000
1!
1%
b00000000000001100100 )
#1035000000
0!
0%
#1040000000
1!
1$
1%
1(
b00000000000000000000 )
#1045000000
0!
0%
#1050000000
1!
0$
1%
0(
b00000000000000000001 )
#1055000000
0!
0%
#1060000000
1!
1%
b00000000000000000010 )
#1065000000
0!
0%
#1070000000
1!
1%
b00000000000000000011 )
#1075000000
0!
0%
#1080000000
1!
1%
b00000000000000000100 )
#1085000000
0!
0%
#1090000000
1!
1%
b00000000000000000101 )
#1095000000
0!
0%
#1100000000
1!
1%
b00000000000000000110 )
#1105000000
0!
0%
#1110000000
1!
1%
b00000000000000000111 )
#1115000000
0!
0%
#1120000000
1!
1%
b00000000000000001000 )
#1125000000
0!
0%
#1130000000
1!
1%
b00000000000000001001 )
#1135000000
0!
0%
#1140000000
1!
1%
b00000000000000001010 )
#1145000000
0!
0%
#1150000000
1!
1%
b00000000000000001011 )
#1155000000
0!
0%
#1160000000
1!
1%
b00000000000000001100 )
#1165000000
0!
0%
#1170000000
1!
1%
b00000000000000001101 )
#1175000000
0!
0%
#1180000000
1!
1%
b00000000000000001110 )
#1185000000
0!
0%
#1190000000
1!
1%
b00000000000000001111 )
#1195000000
0!
0%
#1200000000
1!
1%
b00000000000000010000 )
#1205000000
0!
0%
#1210000000
1!
1%
b00000000000000010001 )
#1215000000
0!
0%
#1220000000
1!
1%
b00000000000000010010 )
#1225000000
0!
0%
#1230000000
1!
1%
b00000000000000010011 )
#1235000000
0!
0%
#1240000000
1!
1%
b00000000000000010100 )
#1245000000
0!
0%
#1250000000
1!
1%
b00000000000000010101 )
#1255000000
0!
0%
#1260000000
1!
1%
b00000000000000010110 )
#1265000000
0!
0%
#1270000000
1!
1%
b00000000000000010111 )
#1275000000
0!
0%
#1280000000
1!
1%
b00000000000000011000 )
#1285000000
0!
0%
#1290000000
1!
1%
b00000000000000011001 )
#1295000000
0!
0%
#1300000000
1!
1%
b00000000000000011010 )
#1305000000
0!
0%
#1310000000
1!
1%
b00000000000000011011 )
#1315000000
0!
0%
#1320000000
1!
1%
b00000000000000011100 )
#1325000000
0!
0%
#1330000000
1!
1%
b00000000000000011101 )
#1335000000
0!
0%
#1340000000
1!
1%
b00000000000000011110 )
#1345000000
0!
0%
#1350000000
1!
1%
b00000000000000011111 )
#1355000000
0!
0%
#1360000000
1!
1%
b00000000000000100000 )
#1365000000
0!
0%
#1370000000
1!
1%
b00000000000000100001 )
#1375000000
0!
0%
#1380000000
1!
1%
b00000000000000100010 )
#1385000000
0!
0%
#1390000000
1!
1%
b00000000000000100011 )
#1395000000
0!
0%
#1400000000
1!
1%
b00000000000000100100 )
#1405000000
0!
0%
#1410000000
1!
1%
b00000000000000100101 )
#1415000000
0!
0%
#1420000000
1!
1%
b00000000000000100110 )
#1425000000
0!
0%
#1430000000
1!
1%
b00000000000000100111 )
#1435000000
0!
0%
#1440000000
1!
1%
b00000000000000101000 )
#1445000000
0!
0%
#1450000000
1!
1%
b00000000000000101001 )
#1455000000
0!
0%
#1460000000
1!
1%
b00000000000000101010 )
#1465000000
0!
0%
#1470000000
1!
1%
b00000000000000101011 )
#1475000000
0!
0%
#1480000000
1!
1%
b00000000000000101100 )
#1485000000
0!
0%
#1490000000
1!
1%
b00000000000000101101 )
#1495000000
0!
0%
#1500000000
1!
1%
b00000000000000101110 )
#1505000000
0!
0%
#1510000000
1!
1%
b00000000000000101111 )
#1515000000
0!
0%
#1520000000
1!
1%
b00000000000000110000 )
#1525000000
0!
0%
#1530000000
1!
1%
b00000000000000110001 )
#1535000000
0!
0%
#1540000000
1!
1%
b00000000000000110010 )
#1545000000
0!
0%
#1550000000
1!
1%
b00000000000000110011 )
#1555000000
0!
0%
#1560000000
1!
1%
b00000000000000110100 )
#1565000000
0!
0%
#1570000000
1!
1%
b00000000000000110101 )
#1575000000
0!
0%
#1580000000
1!
1%
b00000000000000110110 )
#1585000000
0!
0%
#1590000000
1!
1%
b00000000000000110111 )
#1595000000
0!
0%
#1600000000
1!
1%
b00000000000000111000 )
#1605000000
0!
0%
#1610000000
1!
1%
b00000000000000111001 )
#1615000000
0!
0%
#1620000000
1!
1%
b00000000000000111010 )
#1625000000
0!
0%
#1630000000
1!
1%
b00000000000000111011 )
#1635000000
0!
0%
#1640000000
1!
1%
b00000000000000111100 )
#1645000000
0!
0%
#1650000000
1!
1%
b00000000000000111101 )
#1655000000
0!
0%
#1660000000
1!
1%
b00000000000000111110 )
#1665000000
0!
0%
#1670000000
1!
1%
b00000000000000111111 )
#1675000000
0!
0%
#1680000000
1!
1%
b00000000000001000000 )
#1685000000
0!
0%
#1690000000
1!
1%
b00000000000001000001 )
#1695000000
0!
0%
#1700000000
1!
1%
b00000000000001000010 )
#1705000000
0!
0%
#1710000000
1!
1%
b00000000000001000011 )
#1715000000
0!
0%
#1720000000
1!
1%
b00000000000001000100 )
#1725000000
0!
0%
#1730000000
1!
1%
b00000000000001000101 )
#1735000000
0!
0%
#1740000000
1!
1%
b00000000000001000110 )
#1745000000
0!
0%
#1750000000
1!
1%
b00000000000001000111 )
#1755000000
0!
0%
#1760000000
1!
1%
b00000000000001001000 )
#1765000000
0!
0%
#1770000000
1!
1%
b00000000000001001001 )
#1775000000
0!
0%
#1780000000
1!
1%
b00000000000001001010 )
#1785000000
0!
0%
#1790000000
1!
1%
b00000000000001001011 )
#1795000000
0!
0%
#1800000000
1!
1%
b00000000000001001100 )
#1805000000
0!
0%
#1810000000
1!
1%
b00000000000001001101 )
#1815000000
0!
0%
#1820000000
1!
1%
b00000000000001001110 )
#1825000000
0!
0%
#1830000000
1!
1%
b00000000000001001111 )
#1835000000
0!
0%
#1840000000
1!
1%
b00000000000001010000 )
#1845000000
0!
0%
#1850000000
1!
1%
b00000000000001010001 )
#1855000000
0!
0%
#1860000000
1!
1%
b00000000000001010010 )
#1865000000
0!
0%
#1870000000
1!
1%
b00000000000001010011 )
#1875000000
0!
0%
#1880000000
1!
1%
b00000000000001010100 )
#1885000000
0!
0%
#1890000000
1!
1%
b00000000000001010101 )
#1895000000
0!
0%
#1900000000
1!
1%
b00000000000001010110 )
#1905000000
0!
0%
#1910000000
1!
1%
b00000000000001010111 )
#1915000000
0!
0%
#1920000000
1!
1%
b00000000000001011000 )
#1925000000
0!
0%
#1930000000
1!
1%
b00000000000001011001 )
#1935000000
0!
0%
#1940000000
1!
1%
b00000000000001011010 )
#1945000000
0!
0%
#1950000000
1!
1%
b00000000000001011011 )
#1955000000
0!
0%
#1960000000
1!
1%
b00000000000001011100 )
#1965000000
0!
0%
#1970000000
1!
1%
b00000000000001011101 )
#1975000000
0!
0%
#1980000000
1!
1%
b00000000000001011110 )
#1985000000
0!
0%
#1990000000
1!
1%
b00000000000001011111 )
#1995000000
0!
0%
#2000000000
1!
1%
b00000000000001100000 )
#2005000000
0!
0%
#2010000000
1!
1%
b00000000000001100001 )
#2015000000
0!
0%
#2020000000
1!
1%
b00000000000001100010 )
#2025000000
0!
0%
#2030000000
1!
1%
b00000000000001100011 )
#2035000000
0!
0%
#2040000000
1!
1%
b00000000000001100100 )
#2045000000
0!
0%
#2050000000
1!
1$
1%
1(
b00000000000000000000 )
#2055000000
0!
0%
#2060000000
1!
0$
1%
0(
b00000000000000000001 )
#2065000000
0!
0%
#2070000000
1!
1%
b00000000000000000010 )
#2075000000
0!
0%
#2080000000
1!
1%
b00000000000000000011 )
#2085000000
0!
0%
#2090000000
1!
1%
b00000000000000000100 )
#2095000000
0!
0%
#2100000000
1!
1%
b00000000000000000101 )
#2105000000
0!
0%
#2110000000
1!
1%
b00000000000000000110 )
#2115000000
0!
0%
#2120000000
1!
1%
b00000000000000000111 )
#2125000000
0!
0%
#2130000000
1!
1%
b00000000000000001000 )
#2135000000
0!
0%
#2140000000
1!
1%
b00000000000000001001 )
#2145000000
0!
0%
#2150000000
1!
1%
b00000000000000001010 )
#2155000000
0!
0%
#2160000000
1!
1%
b00000000000000001011 )
#2165000000
0!
0%
#2170000000
1!
1%
b00000000000000001100 )
#2175000000
0!
0%
#2180000000
1!
1%
b00000000000000001101 )
#2185000000
0!
0%
#2190000000
1!
1%
b00000000000000001110 )
#2195000000
0!
0%
#2200000000
1!
1%
b00000000000000001111 )
#2205000000
0!
0%
#2210000000
1!
1%
b00000000000000010000 )
#2215000000
0!
0%
#2220000000
1!
1%
b00000000000000010001 )
#2225000000
0!
0%
#2230000000
1!
1%
b00000000000000010010 )
#2235000000
0!
0%
#2240000000
1!
1%
b00000000000000010011 )
#2245000000
0!
0%
#2250000000
1!
1%
b00000000000000010100 )
#2255000000
0!
0%
#2260000000
1!
1%
b00000000000000010101 )
#2265000000
0!
0%
#2270000000
1!
1%
b00000000000000010110 )
#2275000000
0!
0%
#2280000000
1!
1%
b00000000000000010111 )
#2285000000
0!
0%
#2290000000
1!
1%
b00000000000000011000 )
#2295000000
0!
0%
#2300000000
1!
1%
b00000000000000011001 )
#2305000000
0!
0%
#2310000000
1!
1%
b00000000000000011010 )
#2315000000
0!
0%
#2320000000
1!
1%
b00000000000000011011 )
#2325000000
0!
0%
#2330000000
1!
1%
b00000000000000011100 )
#2335000000
0!
0%
#2340000000
1!
1%
b00000000000000011101 )
#2345000000
0!
0%
#2350000000
1!
1%
b00000000000000011110 )
#2355000000
0!
0%
#2360000000
1!
1%
b00000000000000011111 )
#2365000000
0!
0%
#2370000000
1!
1%
b00000000000000100000 )
#2375000000
0!
0%
#2380000000
1!
1%
b00000000000000100001 )
#2385000000
0!
0%
#2390000000
1!
1%
b00000000000000100010 )
#2395000000
0!
0%
#2400000000
1!
1%
b00000000000000100011 )
#2405000000
0!
0%
#2410000000
1!
1%
b00000000000000100100 )
#2415000000
0!
0%
#2420000000
1!
1%
b00000000000000100101 )
#2425000000
0!
0%
#2430000000
1!
1%
b00000000000000100110 )
#2435000000
0!
0%
#2440000000
1!
1%
b00000000000000100111 )
#2445000000
0!
0%
#2450000000
1!
1%
b00000000000000101000 )
#2455000000
0!
0%
#2460000000
1!
1%
b00000000000000101001 )
#2465000000
0!
0%
#2470000000
1!
1%
b00000000000000101010 )
#2475000000
0!
0%
#2480000000
1!
1%
b00000000000000101011 )
#2485000000
0!
0%
#2490000000
1!
1%
b00000000000000101100 )
#2495000000
0!
0%
#2500000000
1!
1%
b00000000000000101101 )
#2505000000
0!
0%
#2510000000
1!
1%
b00000000000000101110 )
#2515000000
0!
0%
#2520000000
1!
1%
b00000000000000101111 )
#2525000000
0!
0%
#2530000000
1!
1%
b00000000000000110000 )
#2535000000
0!
0%
#2540000000
1!
1%
b00000000000000110001 )
#2545000000
0!
0%
#2550000000
1!
1%
b00000000000000110010 )
#2555000000
0!
0%
#2560000000
1!
1%
b00000000000000110011 )
#2565000000
0!
0%
#2570000000
1!
1%
b00000000000000110100 )
#2575000000
0!
0%
#2580000000
1!
1%
b00000000000000110101 )
#2585000000
0!
0%
#2590000000
1!
1%
b00000000000000110110 )
#2595000000
0!
0%
#2600000000
1!
1%
b00000000000000110111 )
#2605000000
0!
0%
#2610000000
1!
1%
b00000000000000111000 )
#2615000000
0!
0%
#2620000000
1!
1%
b00000000000000111001 )
#2625000000
0!
0%
#2630000000
1!
1%
b00000000000000111010 )
#2635000000
0!
0%
#2640000000
1!
1%
b00000000000000111011 )
#2645000000
0!
0%
#2650000000
1!
1%
b00000000000000111100 )
#2655000000
0!
0%
#2660000000
1!
1%
b00000000000000111101 )
#2665000000
0!
0%
#2670000000
1!
1%
b00000000000000111110 )
#2675000000
0!
0%
#2680000000
1!
1%
b00000000000000111111 )
#2685000000
0!
0%
#2690000000
1!
1%
b00000000000001000000 )
#2695000000
0!
0%
#2700000000
1!
1%
b00000000000001000001 )
#2705000000
0!
0%
#2710000000
1!
1%
b00000000000001000010 )
#2715000000
0!
0%
#2720000000
1!
1%
b00000000000001000011 )
#2725000000
0!
0%
#2730000000
1!
1%
b00000000000001000100 )
#2735000000
0!
0%
#2740000000
1!
1%
b00000000000001000101 )
#2745000000
0!
0%
#2750000000
1!
1%
b00000000000001000110 )
#2755000000
0!
0%
#2760000000
1!
1%
b00000000000001000111 )
#2765000000
0!
0%
#2770000000
1!
1%
b00000000000001001000 )
#2775000000
0!
0%
#2780000000
1!
1%
b00000000000001001001 )
#2785000000
0!
0%
#2790000000
1!
1%
b00000000000001001010 )
#2795000000
0!
0%
#2800000000
1!
1%
b00000000000001001011 )
#2805000000
0!
0%
#2810000000
1!
1%
b00000000000001001100 )
#2815000000
0!
0%
#2820000000
1!
1%
b00000000000001001101 )
#2825000000
0!
0%
#2830000000
1!
1%
b00000000000001001110 )
#2835000000
0!
0%
#2840000000
1!
1%
b00000000000001001111 )
#2845000000
0!
0%
#2850000000
1!
1%
b00000000000001010000 )
#2855000000
0!
0%
#2860000000
1!
1%
b00000000000001010001 )
#2865000000
0!
0%
#2870000000
1!
1%
b00000000000001010010 )
#2875000000
0!
0%
#2880000000
1!
1%
b00000000000001010011 )
#2885000000
0!
0%
#2890000000
1!
1%
b00000000000001010100 )
#2895000000
0!
0%
#2900000000
1!
1%
b00000000000001010101 )
#2905000000
0!
0%
#2910000000
1!
1%
b00000000000001010110 )
#2915000000
0!
0%
#2920000000
1!
1%
b00000000000001010111 )
#2925000000
0!
0%
#2930000000
1!
1%
b00000000000001011000 )
#2935000000
0!
0%
#2940000000
1!
1%
b00000000000001011001 )
#2945000000
0!
0%
#2950000000
1!
1%
b00000000000001011010 )
#2955000000
0!
0%
#2960000000
1!
1%
b00000000000001011011 )
#2965000000
0!
0%
#2970000000
1!
1%
b00000000000001011100 )
#2975000000
0!
0%
#2980000000
1!
1%
b00000000000001011101 )
#2985000000
0!
0%
#2990000000
1!
1%
b00000000000001011110 )
#2995000000
0!
0%
#3000000000
1!
1%
b00000000000001011111 )
#3005000000
0!
0%
#3010000000
1!
1%
b00000000000001100000 )
#3015000000
0!
0%
#3020000000
1!
1%
b00000000000001100001 )
#3025000000
0!
0%
#3030000000
1!
1%
b00000000000001100010 )
#3035000000
0!
0%
#3040000000
1!
1%
b00000000000001100011 )
#3045000000
0!
0%
#3050000000
1!
1%
b00000000000001100100 )
#3055000000
0!
0%
#3060000000
1!
1$
1%
1(
b00000000000000000000 )
#3065000000
0!
0%
#3070000000
1!
0$
1%
0(
b00000000000000000001 )
#3075000000
0!
0%
#3080000000
1!
1%
b00000000000000000010 )
#3085000000
0!
0%
#3090000000
1!
1%
b00000000000000000011 )
#3095000000
0!
0%
#3100000000
1!
1%
b00000000000000000100 )
#3105000000
0!
0%
#3110000000
1!
1%
b00000000000000000101 )
#3115000000
0!
0%
#3120000000
1!
1%
b00000000000000000110 )
#3125000000
0!
0%
#3130000000
1!
1%
b00000000000000000111 )
#3135000000
0!
0%
#3140000000
1!
1%
b00000000000000001000 )
#3145000000
0!
0%
#3150000000
1!
1%
b00000000000000001001 )
#3155000000
0!
0%
#3160000000
1!
1%
b00000000000000001010 )
#3165000000
0!
0%
#3170000000
1!
1%
b00000000000000001011 )
#3175000000
0!
0%
#3180000000
1!
1%
b00000000000000001100 )
#3185000000
0!
0%
#3190000000
1!
1%
b00000000000000001101 )
#3195000000
0!
0%
#3200000000
1!
1%
b00000000000000001110 )
#3205000000
0!
0%
#3210000000
1!
1%
b00000000000000001111 )
#3215000000
0!
0%
#3220000000
1!
1%
b00000000000000010000 )
#3225000000
0!
0%
#3230000000
1!
1%
b00000000000000010001 )
#3235000000
0!
0%
#3240000000
1!
1%
b00000000000000010010 )
#3245000000
0!
0%
#3250000000
1!
1%
b00000000000000010011 )
#3255000000
0!
0%
#3260000000
1!
1%
b00000000000000010100 )
#3265000000
0!
0%
#3270000000
1!
1%
b00000000000000010101 )
#3275000000
0!
0%
#3280000000
1!
1%
b00000000000000010110 )
#3285000000
0!
0%
#3290000000
1!
1%
b00000000000000010111 )
#3295000000
0!
0%
#3300000000
1!
1%
b00000000000000011000 )
#3305000000
0!
0%
#3310000000
1!
1%
b00000000000000011001 )
#3315000000
0!
0%
#3320000000
1!
1%
b00000000000000011010 )
#3325000000
0!
0%
#3330000000
1!
1%
b00000000000000011011 )
#3335000000
0!
0%
#3340000000
1!
1%
b00000000000000011100 )
#3345000000
0!
0%
#3350000000
1!
1%
b00000000000000011101 )
#3355000000
0!
0%
#3360000000
1!
1%
b00000000000000011110 )
#3365000000
0!
0%
#3370000000
1!
1%
b00000000000000011111 )
#3375000000
0!
0%
#3380000000
1!
1%
b00000000000000100000 )
#3385000000
0!
0%
#3390000000
1!
1%
b00000000000000100001 )
#3395000000
0!
0%
#3400000000
1!
1%
b00000000000000100010 )
#3405000000
0!
0%
#3410000000
1!
1%
b00000000000000100011 )
#3415000000
0!
0%
#3420000000
1!
1%
b00000000000000100100 )
#3425000000
0!
0%
#3430000000
1!
1%
b00000000000000100101 )
#3435000000
0!
0%
#3440000000
1!
1%
b00000000000000100110 )
#3445000000
0!
0%
#3450000000
1!
1%
b00000000000000100111 )
#3455000000
0!
0%
#3460000000
1!
1%
b00000000000000101000 )
#3465000000
0!
0%
#3470000000
1!
1%
b00000000000000101001 )
#3475000000
0!
0%
#3480000000
1!
1%
b00000000000000101010 )
#3485000000
0!
0%
#3490000000
1!
1%
b00000000000000101011 )
#3495000000
0!
0%
#3500000000
1!
1%
b00000000000000101100 )
#3505000000
0!
0%
#3510000000
1!
1%
b00000000000000101101 )
#3515000000
0!
0%
#3520000000
1!
1%
b00000000000000101110 )
#3525000000
0!
0%
#3530000000
1!
1%
b00000000000000101111 )
#3535000000
0!
0%
#3540000000
1!
1%
b00000000000000110000 )
#3545000000
0!
0%
#3550000000
1!
1%
b00000000000000110001 )
#3555000000
0!
0%
#3560000000
1!
1%
b00000000000000110010 )
#3565000000
0!
0%
#3570000000
1!
1%
b00000000000000110011 )
#3575000000
0!
0%
#3580000000
1!
1%
b00000000000000110100 )
#3585000000
0!
0%
#3590000000
1!
1%
b00000000000000110101 )
#3595000000
0!
0%
#3600000000
1!
1%
b00000000000000110110 )
#3605000000
0!
0%
#3610000000
1!
1%
b00000000000000110111 )
#3615000000
0!
0%
#3620000000
1!
1%
b00000000000000111000 )
#3625000000
0!
0%
#3630000000
1!
1%
b00000000000000111001 )
#3635000000
0!
0%
#3640000000
1!
1%
b00000000000000111010 )
#3645000000
0!
0%
#3650000000
1!
1%
b00000000000000111011 )
#3655000000
0!
0%
#3660000000
1!
1%
b00000000000000111100 )
#3665000000
0!
0%
#3670000000
1!
1%
b00000000000000111101 )
#3675000000
0!
0%
#3680000000
1!
1%
b00000000000000111110 )
#3685000000
0!
0%
#3690000000
1!
1%
b00000000000000111111 )
#3695000000
0!
0%
#3700000000
1!
1%
b00000000000001000000 )
#3705000000
0!
0%
#3710000000
1!
1%
b00000000000001000001 )
#3715000000
0!
0%
#3720000000
1!
1%
b00000000000001000010 )
#3725000000
0!
0%
#3730000000
1!
1%
b00000000000001000011 )
#3735000000
0!
0%
#3740000000
1!
1%
b00000000000001000100 )
#3745000000
0!
0%
#3750000000
1!
1%
b00000000000001000101 )
#3755000000
0!
0%
#3760000000
1!
1%
b00000000000001000110 )
#3765000000
0!
0%
#3770000000
1!
1%
b00000000000001000111 )
#3775000000
0!
0%
#3780000000
1!
1%
b00000000000001001000 )
#3785000000
0!
0%
#3790000000
1!
1%
b00000000000001001001 )
#3795000000
0!
0%
#3800000000
1!
1%
b00000000000001001010 )
#3805000000
0!
0%
#3810000000
1!
1%
b00000000000001001011 )
#3815000000
0!
0%
#3820000000
1!
1%
b00000000000001001100 )
#3825000000
0!
0%
#3830000000
1!
1%
b00000000000001001101 )
#3835000000
0!
0%
#3840000000
1!
1%
b00000000000001001110 )
#3845000000
0!
0%
#3850000000
1!
1%
b00000000000001001111 )
#3855000000
0!
0%
#3860000000
1!
1%
b00000000000001010000 )
#3865000000
0!
0%
#3870000000
1!
1%
b00000000000001010001 )
#3875000000
0!
0%
#3880000000
1!
1%
b00000000000001010010 )
#3885000000
0!
0%
#3890000000
1!
1%
b00000000000001010011 )
#3895000000
0!
0%
#3900000000
1!
1%
b00000000000001010100 )
#3905000000
0!
0%
#3910000000
1!
1%
b00000000000001010101 )
#3915000000
0!
0%
#3920000000
1!
1%
b00000000000001010110 )
#3925000000
0!
0%
#3930000000
1!
1%
b00000000000001010111 )
#3935000000
0!
0%
#3940000000
1!
1%
b00000000000001011000 )
